	[{"id":1,
		"name":"Abia",
		"leadingParty":{"name":"PDP","theme":"red","candidate":"Atiku Abubakar","votes":219698,"votesFormat":"219,698","percent":67.96},
		"accredited":361561,
		"valid":323291,
		"parties":[
			{"name":"PDP","theme":"red","candidate":"Atiku Abubakar","votes":219698,"votesFormat":"219,698","percent":67.96},
			{"name":"APC","theme":"green","candidate":"Muhammadu Buhari","votes":85058,"votesFormat":"85,058","percent":26.31},
			{"name":"APGA","theme":"blue","candidate":"Gbor John Wilson Terwase","votes":9638,"votesFormat":"9,638","percent":2.98},
			{"name":"PCP","theme":"brown","candidate":"Felix Nicolas","votes":1489,"votesFormat":"1,489","percent":0.46},
			{"name":"YPP","theme":"yellow","candidate":"Kingsley Moghalu","votes":720,"votesFormat":"720","percent":0.22},
			{"name":"ADC","theme":"yellow","candidate":"Obadiah Mailafia","votes":336,"votesFormat":"336","percent":0.1},
			{"name":"AAC","theme":"brown","candidate":"Omoyele Sowore","votes":212,"votesFormat":"212","percent":0.07},
			{"name":"ACPN","theme":"purple","candidate":"Oby Ezekwesili","votes":134,"votesFormat":"134","percent":0.04},
			{"name":"ANN","theme":"blue","candidate":"Fela Durotoye","votes":88,"votesFormat":"88","percent":0.03}
			]
	},

	{"id":2,"name":"Adamawa","leadingParty":{"name":"PDP","theme":"red","candidate":"Atiku Abubakar","votes":410266,"votesFormat":"410,266","percent":50.55},"accredited":874920,"valid":811534,"parties":[{"name":"PDP","theme":"red","candidate":"Atiku Abubakar","votes":410266,"votesFormat":"410,266","percent":50.55},{"name":"APC","theme":"green","candidate":"Muhammadu Buhari","votes":378078,"votesFormat":"378,078","percent":46.59},{"name":"ADC","theme":"yellow","candidate":"Obadiah Mailafia","votes":3989,"votesFormat":"3,989","percent":0.49},{"name":"PCP","theme":"brown","candidate":"Felix Nicolas","votes":3670,"votesFormat":"3,670","percent":0.45},{"name":"AAC","theme":"brown","candidate":"Omoyele Sowore","votes":282,"votesFormat":"282","percent":0.03},{"name":"ANN","theme":"blue","candidate":"Fela Durotoye","votes":162,"votesFormat":"162","percent":0.02},{"name":"APGA","theme":"blue","candidate":"Gbor John Wilson Terwase","votes":159,"votesFormat":"159","percent":0.02},{"name":"ACPN","theme":"purple","candidate":"Oby Ezekwesili","votes":138,"votesFormat":"138","percent":0.02},{"name":"YPP","theme":"yellow","candidate":"Kingsley Moghalu","votes":109,"votesFormat":"109","percent":0.01}]},

	{"id":3,"name":"Akwa Ibom","leadingParty":{"name":"PDP","theme":"red","candidate":"Atiku Abubakar","votes":395832,"votesFormat":"395,832","percent":68.39},"accredited":695677,"valid":578775,"parties":[{"name":"PDP","theme":"red","candidate":"Atiku Abubakar","votes":395832,"votesFormat":"395,832","percent":68.39},{"name":"APC","theme":"green","candidate":"Muhammadu Buhari","votes":175429,"votesFormat":"175,429","percent":30.31},{"name":"PCP","theme":"brown","candidate":"Felix Nicolas","votes":1902,"votesFormat":"1,902","percent":0.33},{"name":"ADC","theme":"yellow","candidate":"Obadiah Mailafia","votes":230,"votesFormat":"230","percent":0.04},{"name":"AAC","theme":"brown","candidate":"Omoyele Sowore","votes":222,"votesFormat":"222","percent":0.04},{"name":"YPP","theme":"yellow","candidate":"Kingsley Moghalu","votes":118,"votesFormat":"118","percent":0.02},{"name":"ANN","theme":"blue","candidate":"Fela Durotoye","votes":95,"votesFormat":"95","percent":0.02},{"name":"APGA","theme":"blue","candidate":"Gbor John Wilson Terwase","votes":61,"votesFormat":"61","percent":0.01},{"name":"ACPN","theme":"purple","candidate":"Oby Ezekwesili","votes":55,"votesFormat":"55","percent":0.01}]},

	{"id":4,"name":"Anambra","leadingParty":{"name":"PDP","theme":"red","candidate":"Atiku Abubakar","votes":524738,"votesFormat":"524,738","percent":86.63},"accredited":675273,"valid":605734,"parties":[{"name":"PDP","theme":"red","candidate":"Atiku Abubakar","votes":524738,"votesFormat":"524,738","percent":86.63},{"name":"APC","theme":"green","candidate":"Muhammadu Buhari","votes":33298,"votesFormat":"33,298","percent":5.5},{"name":"APGA","theme":"blue","candidate":"Gbor John Wilson Terwase","votes":30034,"votesFormat":"30,034","percent":4.96},{"name":"PCP","theme":"brown","candidate":"Felix Nicolas","votes":4374,"votesFormat":"4,374","percent":0.72},{"name":"YPP","theme":"yellow","candidate":"Kingsley Moghalu","votes":4091,"votesFormat":"4,091","percent":0.68},{"name":"ADC","theme":"yellow","candidate":"Obadiah Mailafia","votes":227,"votesFormat":"227","percent":0.04},{"name":"AAC","theme":"brown","candidate":"Omoyele Sowore","votes":124,"votesFormat":"124","percent":0.02},{"name":"ACPN","theme":"purple","candidate":"Oby Ezekwesili","votes":109,"votesFormat":"109","percent":0.02},{"name":"ANN","theme":"blue","candidate":"Fela Durotoye","votes":45,"votesFormat":"45","percent":0.01}]},

	{"id":5,"name":"Bauchi","leadingParty":{"name":"APC","theme":"green","candidate":"Muhammadu Buhari","votes":798428,"votesFormat":"798,428","percent":77.95},"accredited":1075330,"valid":1024307,"parties":[{"name":"APC","theme":"green","candidate":"Muhammadu Buhari","votes":798428,"votesFormat":"798,428","percent":77.95},{"name":"PDP","theme":"red","candidate":"Atiku Abubakar","votes":209313,"votesFormat":"209,313","percent":20.43},{"name":"PCP","theme":"brown","candidate":"Felix Nicolas","votes":2104,"votesFormat":"2,104","percent":0.21},{"name":"ADC","theme":"yellow","candidate":"Obadiah Mailafia","votes":296,"votesFormat":"296","percent":0.03},{"name":"AAC","theme":"brown","candidate":"Omoyele Sowore","votes":183,"votesFormat":"183","percent":0.02},{"name":"APGA","theme":"blue","candidate":"Gbor John Wilson Terwase","votes":149,"votesFormat":"149","percent":0.01},{"name":"YPP","theme":"yellow","candidate":"Kingsley Moghalu","votes":112,"votesFormat":"112","percent":0.01},{"name":"ACPN","theme":"purple","candidate":"Oby Ezekwesili","votes":81,"votesFormat":"81","percent":0.01},{"name":"ANN","theme":"blue","candidate":"Fela Durotoye","votes":46,"votesFormat":"46","percent":0}]},

	{"id":6,"name":"Bayelsa","leadingParty":{"name":"PDP","theme":"red","candidate":"Atiku Abubakar","votes":197933,"votesFormat":"197,933","percent":61.51},"accredited":344237,"valid":321767,"parties":[{"name":"PDP","theme":"red","candidate":"Atiku Abubakar","votes":197933,"votesFormat":"197,933","percent":61.51},{"name":"APC","theme":"green","candidate":"Muhammadu Buhari","votes":118821,"votesFormat":"118,821","percent":36.93},{"name":"PCP","theme":"brown","candidate":"Felix Nicolas","votes":1584,"votesFormat":"1,584","percent":0.49},{"name":"ADC","theme":"yellow","candidate":"Obadiah Mailafia","votes":1078,"votesFormat":"1,078","percent":0.34},{"name":"AAC","theme":"brown","candidate":"Omoyele Sowore","votes":126,"votesFormat":"126","percent":0.04},{"name":"ACPN","theme":"purple","candidate":"Oby Ezekwesili","votes":60,"votesFormat":"60","percent":0.02},{"name":"APGA","theme":"blue","candidate":"Gbor John Wilson Terwase","votes":53,"votesFormat":"53","percent":0.02},{"name":"YPP","theme":"yellow","candidate":"Kingsley Moghalu","votes":50,"votesFormat":"50","percent":0.02},{"name":"ANN","theme":"blue","candidate":"Fela Durotoye","votes":37,"votesFormat":"37","percent":0.01}]},

	{"id":7,"name":"Benue","leadingParty":{"name":"PDP","theme":"red","candidate":"Atiku Abubakar","votes":356817,"votesFormat":"356,817","percent":48.95},"accredited":786069,"valid":728912,"parties":[{"name":"PDP","theme":"red","candidate":"Atiku Abubakar","votes":356817,"votesFormat":"356,817","percent":48.95},{"name":"APC","theme":"green","candidate":"Muhammadu Buhari","votes":347668,"votesFormat":"347,668","percent":47.7},{"name":"APGA","theme":"blue","candidate":"Gbor John Wilson Terwase","votes":4582,"votesFormat":"4,582","percent":0.63},{"name":"PCP","theme":"brown","candidate":"Felix Nicolas","votes":2793,"votesFormat":"2,793","percent":0.38},{"name":"YPP","theme":"yellow","candidate":"Kingsley Moghalu","votes":557,"votesFormat":"557","percent":0.08},{"name":"ADC","theme":"yellow","candidate":"Obadiah Mailafia","votes":554,"votesFormat":"554","percent":0.08},{"name":"AAC","theme":"brown","candidate":"Omoyele Sowore","votes":309,"votesFormat":"309","percent":0.04},{"name":"ACPN","theme":"purple","candidate":"Oby Ezekwesili","votes":238,"votesFormat":"238","percent":0.03},{"name":"ANN","theme":"blue","candidate":"Fela Durotoye","votes":201,"votesFormat":"201","percent":0.03}]},

	{"id":8,"name":"Borno","leadingParty":{"name":"APC","theme":"green","candidate":"Muhammadu Buhari","votes":836496,"votesFormat":"836,496","percent":90.94},"accredited":987290,"valid":919786,"parties":[{"name":"APC","theme":"green","candidate":"Muhammadu Buhari","votes":836496,"votesFormat":"836,496","percent":90.94},{"name":"PDP","theme":"red","candidate":"Atiku Abubakar","votes":71788,"votesFormat":"71,788","percent":7.8},{"name":"PCP","theme":"brown","candidate":"Felix Nicolas","votes":1563,"votesFormat":"1,563","percent":0.17},{"name":"ADC","theme":"yellow","candidate":"Obadiah Mailafia","votes":301,"votesFormat":"301","percent":0.03},{"name":"AAC","theme":"brown","candidate":"Omoyele Sowore","votes":269,"votesFormat":"269","percent":0.03},{"name":"APGA","theme":"blue","candidate":"Gbor John Wilson Terwase","votes":187,"votesFormat":"187","percent":0.02},{"name":"ACPN","theme":"purple","candidate":"Oby Ezekwesili","votes":125,"votesFormat":"125","percent":0.01},{"name":"YPP","theme":"yellow","candidate":"Kingsley Moghalu","votes":78,"votesFormat":"78","percent":0.01},{"name":"ANN","theme":"blue","candidate":"Fela Durotoye","votes":29,"votesFormat":"29","percent":0}]},

	{"id":9,"name":"Cross River","leadingParty":{"name":"PDP","theme":"red","candidate":"Atiku Abubakar","votes":295737,"votesFormat":"295,737","percent":70.1},"accredited":461033,"valid":421901,"parties":[{"name":"PDP","theme":"red","candidate":"Atiku Abubakar","votes":295737,"votesFormat":"295,737","percent":70.1},{"name":"APC","theme":"green","candidate":"Muhammadu Buhari","votes":117302,"votesFormat":"117,302","percent":27.8},{"name":"PCP","theme":"brown","candidate":"Felix Nicolas","votes":2033,"votesFormat":"2,033","percent":0.48},{"name":"ADC","theme":"yellow","candidate":"Obadiah Mailafia","votes":326,"votesFormat":"326","percent":0.08},{"name":"AAC","theme":"brown","candidate":"Omoyele Sowore","votes":242,"votesFormat":"242","percent":0.06},{"name":"YPP","theme":"yellow","candidate":"Kingsley Moghalu","votes":217,"votesFormat":"217","percent":0.05},{"name":"ANN","theme":"blue","candidate":"Fela Durotoye","votes":88,"votesFormat":"88","percent":0.02},{"name":"ACPN","theme":"purple","candidate":"Oby Ezekwesili","votes":45,"votesFormat":"45","percent":0.01},{"name":"APGA","theme":"blue","candidate":"Gbor John Wilson Terwase","votes":43,"votesFormat":"43","percent":0.01}]},

	{"id":10,"name":"Delta","leadingParty":{"name":"PDP","theme":"red","candidate":"Atiku Abubakar","votes":594068,"votesFormat":"594,068","percent":71.59},"accredited":891647,"valid":829762,"parties":[{"name":"PDP","theme":"red","candidate":"Atiku Abubakar","votes":594068,"votesFormat":"594,068","percent":71.59},{"name":"APC","theme":"green","candidate":"Muhammadu Buhari","votes":221292,"votesFormat":"221,292","percent":26.67},{"name":"PCP","theme":"brown","candidate":"Felix Nicolas","votes":2753,"votesFormat":"2,753","percent":0.33},{"name":"AAC","theme":"brown","candidate":"Omoyele Sowore","votes":1626,"votesFormat":"1,626","percent":0.2},{"name":"ADC","theme":"yellow","candidate":"Obadiah Mailafia","votes":1075,"votesFormat":"1,075","percent":0.13},{"name":"YPP","theme":"yellow","candidate":"Kingsley Moghalu","votes":497,"votesFormat":"497","percent":0.06},{"name":"ANN","theme":"blue","candidate":"Fela Durotoye","votes":320,"votesFormat":"320","percent":0.04},{"name":"APGA","theme":"blue","candidate":"Gbor John Wilson Terwase","votes":145,"votesFormat":"145","percent":0.02},{"name":"ACPN","theme":"purple","candidate":"Oby Ezekwesili","votes":134,"votesFormat":"134","percent":0.02}]},

	{"id":11,"name":"Ebonyi","leadingParty":{"name":"PDP","theme":"red","candidate":"Atiku Abubakar","votes":258573,"votesFormat":"258,573","percent":72},"accredited":391747,"valid":359131,"parties":[{"name":"PDP","theme":"red","candidate":"Atiku Abubakar","votes":258573,"votesFormat":"258,573","percent":72},{"name":"APC","theme":"green","candidate":"Muhammadu Buhari","votes":90726,"votesFormat":"90,726","percent":25.26},{"name":"PCP","theme":"brown","candidate":"Felix Nicolas","votes":1637,"votesFormat":"1,637","percent":0.46},{"name":"ANN","theme":"blue","candidate":"Fela Durotoye","votes":683,"votesFormat":"683","percent":0.19},{"name":"APGA","theme":"blue","candidate":"Gbor John Wilson Terwase","votes":222,"votesFormat":"222","percent":0.06},{"name":"ADC","theme":"yellow","candidate":"Obadiah Mailafia","votes":213,"votesFormat":"213","percent":0.06},{"name":"AAC","theme":"brown","candidate":"Omoyele Sowore","votes":205,"votesFormat":"205","percent":0.06},{"name":"YPP","theme":"yellow","candidate":"Kingsley Moghalu","votes":192,"votesFormat":"192","percent":0.05},{"name":"ACPN","theme":"purple","candidate":"Oby Ezekwesili","votes":57,"votesFormat":"57","percent":0.02}]},

	{"id":12,"name":"Edo","leadingParty":{"name":"PDP","theme":"red","candidate":"Atiku Abubakar","votes":275691,"votesFormat":"275,691","percent":49.17},"accredited":604915,"valid":560711,"parties":[{"name":"PDP","theme":"red","candidate":"Atiku Abubakar","votes":275691,"votesFormat":"275,691","percent":49.17},{"name":"APC","theme":"green","candidate":"Muhammadu Buhari","votes":267842,"votesFormat":"267,842","percent":47.77},{"name":"PCP","theme":"brown","candidate":"Felix Nicolas","votes":3526,"votesFormat":"3,526","percent":0.63},{"name":"AAC","theme":"brown","candidate":"Omoyele Sowore","votes":3106,"votesFormat":"3,106","percent":0.55},{"name":"ADC","theme":"yellow","candidate":"Obadiah Mailafia","votes":850,"votesFormat":"850","percent":0.15},{"name":"YPP","theme":"yellow","candidate":"Kingsley Moghalu","votes":531,"votesFormat":"531","percent":0.09},{"name":"ANN","theme":"blue","candidate":"Fela Durotoye","votes":273,"votesFormat":"273","percent":0.05},{"name":"ACPN","theme":"purple","candidate":"Oby Ezekwesili","votes":210,"votesFormat":"210","percent":0.04},{"name":"APGA","theme":"blue","candidate":"Gbor John Wilson Terwase","votes":143,"votesFormat":"143","percent":0.03}]},

	{"id":13,"name":"Ekiti","leadingParty":{"name":"APC","theme":"green","candidate":"Muhammadu Buhari","votes":219231,"votesFormat":"219,231","percent":57.52},"accredited":395741,"valid":381132,"parties":[{"name":"APC","theme":"green","candidate":"Muhammadu Buhari","votes":219231,"votesFormat":"219,231","percent":57.52},{"name":"PDP","theme":"red","candidate":"Atiku Abubakar","votes":154032,"votesFormat":"154,032","percent":40.41},{"name":"PCP","theme":"brown","candidate":"Felix Nicolas","votes":2299,"votesFormat":"2,299","percent":0.6},{"name":"ADC","theme":"yellow","candidate":"Obadiah Mailafia","votes":406,"votesFormat":"406","percent":0.11},{"name":"AAC","theme":"brown","candidate":"Omoyele Sowore","votes":400,"votesFormat":"400","percent":0.1},{"name":"ACPN","theme":"purple","candidate":"Oby Ezekwesili","votes":99,"votesFormat":"99","percent":0.03},{"name":"ANN","theme":"blue","candidate":"Fela Durotoye","votes":88,"votesFormat":"88","percent":0.02},{"name":"YPP","theme":"yellow","candidate":"Kingsley Moghalu","votes":68,"votesFormat":"68","percent":0.02},{"name":"APGA","theme":"blue","candidate":"Gbor John Wilson Terwase","votes":39,"votesFormat":"39","percent":0.01}]},

	{"id":14,"name":"Enugu","leadingParty":{"name":"PDP","theme":"red","candidate":"Atiku Abubakar","votes":355553,"votesFormat":"355,553","percent":84.45},"accredited":452765,"valid":421014,"parties":[{"name":"PDP","theme":"red","candidate":"Atiku Abubakar","votes":355553,"votesFormat":"355,553","percent":84.45},{"name":"APC","theme":"green","candidate":"Muhammadu Buhari","votes":54423,"votesFormat":"54,423","percent":12.93},{"name":"PCP","theme":"brown","candidate":"Felix Nicolas","votes":2337,"votesFormat":"2,337","percent":0.56},{"name":"APGA","theme":"blue","candidate":"Gbor John Wilson Terwase","votes":1618,"votesFormat":"1,618","percent":0.38},{"name":"YPP","theme":"yellow","candidate":"Kingsley Moghalu","votes":1379,"votesFormat":"1,379","percent":0.33},{"name":"ADC","theme":"yellow","candidate":"Obadiah Mailafia","votes":348,"votesFormat":"348","percent":0.08},{"name":"AAC","theme":"brown","candidate":"Omoyele Sowore","votes":219,"votesFormat":"219","percent":0.05},{"name":"ANN","theme":"blue","candidate":"Fela Durotoye","votes":141,"votesFormat":"141","percent":0.03},{"name":"ACPN","theme":"purple","candidate":"Oby Ezekwesili","votes":80,"votesFormat":"80","percent":0.02}]},

	{"id":37,"name":"FCT","leadingParty":{"name":"PDP","theme":"red","candidate":"Atiku Abubakar","votes":259997,"votesFormat":"259,997","percent":61.33},"accredited":467784,"valid":423951,"parties":[{"name":"PDP","theme":"red","candidate":"Atiku Abubakar","votes":259997,"votesFormat":"259,997","percent":61.33},{"name":"APC","theme":"green","candidate":"Muhammadu Buhari","votes":152224,"votesFormat":"152,224","percent":35.91},{"name":"PCP","theme":"brown","candidate":"Felix Nicolas","votes":2921,"votesFormat":"2,921","percent":0.69},{"name":"YPP","theme":"yellow","candidate":"Kingsley Moghalu","votes":1083,"votesFormat":"1,083","percent":0.26},{"name":"ANN","theme":"blue","candidate":"Fela Durotoye","votes":652,"votesFormat":"652","percent":0.15},{"name":"AAC","theme":"brown","candidate":"Omoyele Sowore","votes":583,"votesFormat":"583","percent":0.14},{"name":"APGA","theme":"blue","candidate":"Gbor John Wilson Terwase","votes":255,"votesFormat":"255","percent":0.06},{"name":"ADC","theme":"yellow","candidate":"Obadiah Mailafia","votes":246,"votesFormat":"246","percent":0.06},{"name":"ACPN","theme":"purple","candidate":"Oby Ezekwesili","votes":48,"votesFormat":"48","percent":0.01}]},

	{"id":15,"name":"Gombe","leadingParty":{"name":"APC","theme":"green","candidate":"Muhammadu Buhari","votes":402961,"votesFormat":"402,961","percent":72.71},"accredited":604240,"valid":554203,"parties":[{"name":"APC","theme":"green","candidate":"Muhammadu Buhari","votes":402961,"votesFormat":"402,961","percent":72.71},{"name":"PDP","theme":"red","candidate":"Atiku Abubakar","votes":138484,"votesFormat":"138,484","percent":24.99},{"name":"PCP","theme":"brown","candidate":"Felix Nicolas","votes":1679,"votesFormat":"1,679","percent":0.3},{"name":"ACPN","theme":"purple","candidate":"Oby Ezekwesili","votes":732,"votesFormat":"732","percent":0.13},{"name":"ADC","theme":"yellow","candidate":"Obadiah Mailafia","votes":248,"votesFormat":"248","percent":0.04},{"name":"AAC","theme":"brown","candidate":"Omoyele Sowore","votes":165,"votesFormat":"165","percent":0.03},{"name":"APGA","theme":"blue","candidate":"Gbor John Wilson Terwase","votes":124,"votesFormat":"124","percent":0.02},{"name":"ANN","theme":"blue","candidate":"Fela Durotoye","votes":78,"votesFormat":"78","percent":0.01},{"name":"YPP","theme":"yellow","candidate":"Kingsley Moghalu","votes":39,"votesFormat":"39","percent":0.01}]},

	{"id":16,"name":"Imo","leadingParty":{"name":"PDP","theme":"red","candidate":"Atiku Abubakar","votes":334923,"votesFormat":"334,923","percent":65.47},"accredited":585741,"valid":511586,"parties":[{"name":"PDP","theme":"red","candidate":"Atiku Abubakar","votes":334923,"votesFormat":"334,923","percent":65.47},{"name":"APC","theme":"green","candidate":"Muhammadu Buhari","votes":140463,"votesFormat":"140,463","percent":27.46},{"name":"APGA","theme":"blue","candidate":"Gbor John Wilson Terwase","votes":10880,"votesFormat":"10,880","percent":2.13},{"name":"PCP","theme":"brown","candidate":"Felix Nicolas","votes":4883,"votesFormat":"4,883","percent":0.95},{"name":"YPP","theme":"yellow","candidate":"Kingsley Moghalu","votes":676,"votesFormat":"676","percent":0.13},{"name":"ADC","theme":"yellow","candidate":"Obadiah Mailafia","votes":541,"votesFormat":"541","percent":0.11},{"name":"AAC","theme":"brown","candidate":"Omoyele Sowore","votes":467,"votesFormat":"467","percent":0.09},{"name":"ACPN","theme":"purple","candidate":"Oby Ezekwesili","votes":167,"votesFormat":"167","percent":0.03},{"name":"ANN","theme":"blue","candidate":"Fela Durotoye","votes":119,"votesFormat":"119","percent":0.02}]},

	{"id":17,"name":"Jigawa","leadingParty":{"name":"APC","theme":"green","candidate":"Muhammadu Buhari","votes":794738,"votesFormat":"794,738","percent":71.84},"accredited":1171801,"valid":1106244,"parties":[{"name":"APC","theme":"green","candidate":"Muhammadu Buhari","votes":794738,"votesFormat":"794,738","percent":71.84},{"name":"PDP","theme":"red","candidate":"Atiku Abubakar","votes":289895,"votesFormat":"289,895","percent":26.21},{"name":"PCP","theme":"brown","candidate":"Felix Nicolas","votes":2761,"votesFormat":"2,761","percent":0.25},{"name":"ADC","theme":"yellow","candidate":"Obadiah Mailafia","votes":261,"votesFormat":"261","percent":0.02},{"name":"AAC","theme":"brown","candidate":"Omoyele Sowore","votes":226,"votesFormat":"226","percent":0.02},{"name":"APGA","theme":"blue","candidate":"Gbor John Wilson Terwase","votes":140,"votesFormat":"140","percent":0.01},{"name":"ACPN","theme":"purple","candidate":"Oby Ezekwesili","votes":97,"votesFormat":"97","percent":0.01},{"name":"YPP","theme":"yellow","candidate":"Kingsley Moghalu","votes":67,"votesFormat":"67","percent":0.01},{"name":"ANN","theme":"blue","candidate":"Fela Durotoye","votes":66,"votesFormat":"66","percent":0.01}]},

	{"id":18,"name":"Kaduna","leadingParty":{"name":"APC","theme":"green","candidate":"Muhammadu Buhari","votes":993445,"votesFormat":"993,445","percent":59.72},"accredited":1757868,"valid":1663603,"parties":[{"name":"APC","theme":"green","candidate":"Muhammadu Buhari","votes":993445,"votesFormat":"993,445","percent":59.72},{"name":"PDP","theme":"red","candidate":"Atiku Abubakar","votes":649612,"votesFormat":"649,612","percent":39.05},{"name":"PCP","theme":"brown","candidate":"Felix Nicolas","votes":4027,"votesFormat":"4,027","percent":0.24},{"name":"APGA","theme":"blue","candidate":"Gbor John Wilson Terwase","votes":749,"votesFormat":"749","percent":0.05},{"name":"ADC","theme":"yellow","candidate":"Obadiah Mailafia","votes":558,"votesFormat":"558","percent":0.03},{"name":"ANN","theme":"blue","candidate":"Fela Durotoye","votes":261,"votesFormat":"261","percent":0.02},{"name":"AAC","theme":"brown","candidate":"Omoyele Sowore","votes":243,"votesFormat":"243","percent":0.01},{"name":"YPP","theme":"yellow","candidate":"Kingsley Moghalu","votes":196,"votesFormat":"196","percent":0.01},{"name":"ACPN","theme":"purple","candidate":"Oby Ezekwesili","votes":108,"votesFormat":"108","percent":0.01}]},

	{"id":19,"name":"Kano","leadingParty":{"name":"APC","theme":"green","candidate":"Muhammadu Buhari","votes":1464768,"votesFormat":"1,464,768","percent":77.45},"accredited":2006410,"valid":1891134,"parties":[{"name":"APC","theme":"green","candidate":"Muhammadu Buhari","votes":1464768,"votesFormat":"1,464,768","percent":77.45},{"name":"PDP","theme":"red","candidate":"Atiku Abubakar","votes":391593,"votesFormat":"391,593","percent":20.71},{"name":"PCP","theme":"brown","candidate":"Felix Nicolas","votes":3568,"votesFormat":"3,568","percent":0.19},{"name":"ADC","theme":"yellow","candidate":"Obadiah Mailafia","votes":591,"votesFormat":"591","percent":0.03},{"name":"APGA","theme":"blue","candidate":"Gbor John Wilson Terwase","votes":549,"votesFormat":"549","percent":0.03},{"name":"AAC","theme":"brown","candidate":"Omoyele Sowore","votes":416,"votesFormat":"416","percent":0.02},{"name":"YPP","theme":"yellow","candidate":"Kingsley Moghalu","votes":200,"votesFormat":"200","percent":0.01},{"name":"ACPN","theme":"purple","candidate":"Oby Ezekwesili","votes":194,"votesFormat":"194","percent":0.01},{"name":"ANN","theme":"blue","candidate":"Fela Durotoye","votes":114,"votesFormat":"114","percent":0.01}]},

	{"id":20,"name":"Katsina","leadingParty":{"name":"APC","theme":"green","candidate":"Muhammadu Buhari","votes":1232133,"votesFormat":"1,232,133","percent":79.21},"accredited":1628865,"valid":1555473,"parties":[{"name":"APC","theme":"green","candidate":"Muhammadu Buhari","votes":1232133,"votesFormat":"1,232,133","percent":79.21},{"name":"PDP","theme":"red","candidate":"Atiku Abubakar","votes":308056,"votesFormat":"308,056","percent":19.8},{"name":"PCP","theme":"brown","candidate":"Felix Nicolas","votes":2399,"votesFormat":"2,399","percent":0.15},{"name":"APGA","theme":"blue","candidate":"Gbor John Wilson Terwase","votes":331,"votesFormat":"331","percent":0.02},{"name":"ADC","theme":"yellow","candidate":"Obadiah Mailafia","votes":237,"votesFormat":"237","percent":0.02},{"name":"AAC","theme":"brown","candidate":"Omoyele Sowore","votes":186,"votesFormat":"186","percent":0.01},{"name":"ACPN","theme":"purple","candidate":"Oby Ezekwesili","votes":84,"votesFormat":"84","percent":0.01},{"name":"ANN","theme":"blue","candidate":"Fela Durotoye","votes":82,"votesFormat":"82","percent":0.01},{"name":"YPP","theme":"yellow","candidate":"Kingsley Moghalu","votes":61,"votesFormat":"61","percent":0}]},

	{"id":21,"name":"Kebbi","leadingParty":{"name":"APC","theme":"green","candidate":"Muhammadu Buhari","votes":581552,"votesFormat":"581,552","percent":76.86},"accredited":835238,"valid":756605,"parties":[{"name":"APC","theme":"green","candidate":"Muhammadu Buhari","votes":581552,"votesFormat":"581,552","percent":76.86},{"name":"PDP","theme":"red","candidate":"Atiku Abubakar","votes":154282,"votesFormat":"154,282","percent":20.39},{"name":"PCP","theme":"brown","candidate":"Felix Nicolas","votes":1794,"votesFormat":"1,794","percent":0.24},{"name":"ADC","theme":"yellow","candidate":"Obadiah Mailafia","votes":285,"votesFormat":"285","percent":0.04},{"name":"AAC","theme":"brown","candidate":"Omoyele Sowore","votes":276,"votesFormat":"276","percent":0.04},{"name":"APGA","theme":"blue","candidate":"Gbor John Wilson Terwase","votes":228,"votesFormat":"228","percent":0.03},{"name":"ACPN","theme":"purple","candidate":"Oby Ezekwesili","votes":130,"votesFormat":"130","percent":0.02},{"name":"ANN","theme":"blue","candidate":"Fela Durotoye","votes":99,"votesFormat":"99","percent":0.01},{"name":"YPP","theme":"yellow","candidate":"Kingsley Moghalu","votes":53,"votesFormat":"53","percent":0.01}]},

	{"id":22,"name":"Kogi","leadingParty":{"name":"APC","theme":"green","candidate":"Muhammadu Buhari","votes":285894,"votesFormat":"285,894","percent":54.87},"accredited":570773,"valid":521016,"parties":[{"name":"APC","theme":"green","candidate":"Muhammadu Buhari","votes":285894,"votesFormat":"285,894","percent":54.87},{"name":"PDP","theme":"red","candidate":"Atiku Abubakar","votes":218207,"votesFormat":"218,207","percent":41.88},{"name":"ADC","theme":"yellow","candidate":"Obadiah Mailafia","votes":4369,"votesFormat":"4,369","percent":0.84},{"name":"PCP","theme":"brown","candidate":"Felix Nicolas","votes":2207,"votesFormat":"2,207","percent":0.42},{"name":"APGA","theme":"blue","candidate":"Gbor John Wilson Terwase","votes":318,"votesFormat":"318","percent":0.06},{"name":"AAC","theme":"brown","candidate":"Omoyele Sowore","votes":250,"votesFormat":"250","percent":0.05},{"name":"ACPN","theme":"purple","candidate":"Oby Ezekwesili","votes":204,"votesFormat":"204","percent":0.04},{"name":"ANN","theme":"blue","candidate":"Fela Durotoye","votes":89,"votesFormat":"89","percent":0.02},{"name":"YPP","theme":"yellow","candidate":"Kingsley Moghalu","votes":87,"votesFormat":"87","percent":0.02}]},

	{"id":23,"name":"Kwara","leadingParty":{"name":"APC","theme":"green","candidate":"Muhammadu Buhari","votes":308984,"votesFormat":"308,984","percent":67.22},"accredited":489482,"valid":459676,"parties":[{"name":"APC","theme":"green","candidate":"Muhammadu Buhari","votes":308984,"votesFormat":"308,984","percent":67.22},{"name":"PDP","theme":"red","candidate":"Atiku Abubakar","votes":138184,"votesFormat":"138,184","percent":30.06},{"name":"PCP","theme":"brown","candidate":"Felix Nicolas","votes":2108,"votesFormat":"2,108","percent":0.46},{"name":"ADC","theme":"yellow","candidate":"Obadiah Mailafia","votes":456,"votesFormat":"456","percent":0.1},{"name":"ANN","theme":"blue","candidate":"Fela Durotoye","votes":422,"votesFormat":"422","percent":0.09},{"name":"AAC","theme":"brown","candidate":"Omoyele Sowore","votes":401,"votesFormat":"401","percent":0.09},{"name":"ACPN","theme":"purple","candidate":"Oby Ezekwesili","votes":171,"votesFormat":"171","percent":0.04},{"name":"YPP","theme":"yellow","candidate":"Kingsley Moghalu","votes":140,"votesFormat":"140","percent":0.03},{"name":"APGA","theme":"blue","candidate":"Gbor John Wilson Terwase","votes":89,"votesFormat":"89","percent":0.02}]},

	{"id":24,"name":"Lagos","leadingParty":{"name":"APC","theme":"green","candidate":"Muhammadu Buhari","votes":580825,"votesFormat":"580,825","percent":53.31},"accredited":1196490,"valid":1089567,"parties":[{"name":"APC","theme":"green","candidate":"Muhammadu Buhari","votes":580825,"votesFormat":"580,825","percent":53.31},{"name":"PDP","theme":"red","candidate":"Atiku Abubakar","votes":448015,"votesFormat":"448,015","percent":41.12},{"name":"AAC","theme":"brown","candidate":"Omoyele Sowore","votes":8910,"votesFormat":"8,910","percent":0.82},{"name":"PCP","theme":"brown","candidate":"Felix Nicolas","votes":8458,"votesFormat":"8,458","percent":0.78},{"name":"ANN","theme":"blue","candidate":"Fela Durotoye","votes":6946,"votesFormat":"6,946","percent":0.64},{"name":"YPP","theme":"yellow","candidate":"Kingsley Moghalu","votes":5733,"votesFormat":"5,733","percent":0.53},{"name":"ADC","theme":"yellow","candidate":"Obadiah Mailafia","votes":2915,"votesFormat":"2,915","percent":0.27},{"name":"ACPN","theme":"purple","candidate":"Oby Ezekwesili","votes":572,"votesFormat":"572","percent":0.05},{"name":"APGA","theme":"blue","candidate":"Gbor John Wilson Terwase","votes":499,"votesFormat":"499","percent":0.05}]},

	{"id":25,"name":"Nasarawa","leadingParty":{"name":"APC","theme":"green","candidate":"Muhammadu Buhari","votes":289903,"votesFormat":"289,903","percent":49.92},"accredited":613720,"valid":580778,"parties":[{"name":"APC","theme":"green","candidate":"Muhammadu Buhari","votes":289903,"votesFormat":"289,903","percent":49.92},{"name":"PDP","theme":"red","candidate":"Atiku Abubakar","votes":283847,"votesFormat":"283,847","percent":48.87},{"name":"PCP","theme":"brown","candidate":"Felix Nicolas","votes":1868,"votesFormat":"1,868","percent":0.32},{"name":"APGA","theme":"blue","candidate":"Gbor John Wilson Terwase","votes":1523,"votesFormat":"1,523","percent":0.26},{"name":"ADC","theme":"yellow","candidate":"Obadiah Mailafia","votes":339,"votesFormat":"339","percent":0.06},{"name":"AAC","theme":"brown","candidate":"Omoyele Sowore","votes":75,"votesFormat":"75","percent":0.01},{"name":"ANN","theme":"blue","candidate":"Fela Durotoye","votes":45,"votesFormat":"45","percent":0.01},{"name":"YPP","theme":"yellow","candidate":"Kingsley Moghalu","votes":44,"votesFormat":"44","percent":0.01},{"name":"ACPN","theme":"purple","candidate":"Oby Ezekwesili","votes":28,"votesFormat":"28","percent":0}]},

	{"id":26,"name":"Niger","leadingParty":{"name":"APC","theme":"green","candidate":"Muhammadu Buhari","votes":612371,"votesFormat":"612,371","percent":71.88},"accredited":911964,"valid":851937,"parties":[{"name":"APC","theme":"green","candidate":"Muhammadu Buhari","votes":612371,"votesFormat":"612,371","percent":71.88},{"name":"PDP","theme":"red","candidate":"Atiku Abubakar","votes":218052,"votesFormat":"218,052","percent":25.59},{"name":"PCP","theme":"brown","candidate":"Felix Nicolas","votes":2855,"votesFormat":"2,855","percent":0.34},{"name":"ADC","theme":"yellow","candidate":"Obadiah Mailafia","votes":588,"votesFormat":"588","percent":0.07},{"name":"APGA","theme":"blue","candidate":"Gbor John Wilson Terwase","votes":389,"votesFormat":"389","percent":0.05},{"name":"AAC","theme":"brown","candidate":"Omoyele Sowore","votes":324,"votesFormat":"324","percent":0.04},{"name":"ANN","theme":"blue","candidate":"Fela Durotoye","votes":145,"votesFormat":"145","percent":0.02},{"name":"ACPN","theme":"purple","candidate":"Oby Ezekwesili","votes":137,"votesFormat":"137","percent":0.02},{"name":"YPP","theme":"yellow","candidate":"Kingsley Moghalu","votes":113,"votesFormat":"113","percent":0.01}]},

	{"id":27,"name":"Ogun","leadingParty":{"name":"APC","theme":"green","candidate":"Muhammadu Buhari","votes":281762,"votesFormat":"281,762","percent":49.94},"accredited":613397,"valid":564256,"parties":[{"name":"APC","theme":"green","candidate":"Muhammadu Buhari","votes":281762,"votesFormat":"281,762","percent":49.94},{"name":"PDP","theme":"red","candidate":"Atiku Abubakar","votes":194655,"votesFormat":"194,655","percent":34.5},{"name":"ADC","theme":"yellow","candidate":"Obadiah Mailafia","votes":25283,"votesFormat":"25,283","percent":4.48},{"name":"PCP","theme":"brown","candidate":"Felix Nicolas","votes":3563,"votesFormat":"3,563","percent":0.63},{"name":"AAC","theme":"brown","candidate":"Omoyele Sowore","votes":3196,"votesFormat":"3,196","percent":0.57},{"name":"ANN","theme":"blue","candidate":"Fela Durotoye","votes":1509,"votesFormat":"1,509","percent":0.27},{"name":"ACPN","theme":"purple","candidate":"Oby Ezekwesili","votes":914,"votesFormat":"914","percent":0.16},{"name":"YPP","theme":"yellow","candidate":"Kingsley Moghalu","votes":553,"votesFormat":"553","percent":0.1},{"name":"APGA","theme":"blue","candidate":"Gbor John Wilson Terwase","votes":222,"votesFormat":"222","percent":0.04}]},

	{"id":28,"name":"Ondo","leadingParty":{"name":"PDP","theme":"red","candidate":"Atiku Abubakar","votes":275901,"votesFormat":"275,901","percent":49.62},"accredited":598586,"valid":555994,"parties":[{"name":"PDP","theme":"red","candidate":"Atiku Abubakar","votes":275901,"votesFormat":"275,901","percent":49.62},{"name":"APC","theme":"green","candidate":"Muhammadu Buhari","votes":241769,"votesFormat":"241,769","percent":43.48},{"name":"ADC","theme":"yellow","candidate":"Obadiah Mailafia","votes":6296,"votesFormat":"6,296","percent":1.13},{"name":"PCP","theme":"brown","candidate":"Felix Nicolas","votes":4829,"votesFormat":"4,829","percent":0.87},{"name":"AAC","theme":"brown","candidate":"Omoyele Sowore","votes":4414,"votesFormat":"4,414","percent":0.79},{"name":"YPP","theme":"yellow","candidate":"Kingsley Moghalu","votes":1224,"votesFormat":"1,224","percent":0.22},{"name":"ACPN","theme":"purple","candidate":"Oby Ezekwesili","votes":414,"votesFormat":"414","percent":0.07},{"name":"ANN","theme":"blue","candidate":"Fela Durotoye","votes":311,"votesFormat":"311","percent":0.06},{"name":"APGA","theme":"blue","candidate":"Gbor John Wilson Terwase","votes":90,"votesFormat":"90","percent":0.02}]},

	{"id":29,"name":"Osun","leadingParty":{"name":"APC","theme":"green","candidate":"Muhammadu Buhari","votes":347634,"votesFormat":"347,634","percent":48.64},"accredited":732984,"valid":714682,"parties":[{"name":"APC","theme":"green","candidate":"Muhammadu Buhari","votes":347634,"votesFormat":"347,634","percent":48.64},{"name":"PDP","theme":"red","candidate":"Atiku Abubakar","votes":337377,"votesFormat":"337,377","percent":47.21},{"name":"PCP","theme":"brown","candidate":"Felix Nicolas","votes":4888,"votesFormat":"4,888","percent":0.68},{"name":"ADC","theme":"yellow","candidate":"Obadiah Mailafia","votes":1525,"votesFormat":"1,525","percent":0.21},{"name":"AAC","theme":"brown","candidate":"Omoyele Sowore","votes":1022,"votesFormat":"1,022","percent":0.14},{"name":"ACPN","theme":"purple","candidate":"Oby Ezekwesili","votes":297,"votesFormat":"297","percent":0.04},{"name":"ANN","theme":"blue","candidate":"Fela Durotoye","votes":268,"votesFormat":"268","percent":0.04},{"name":"YPP","theme":"yellow","candidate":"Kingsley Moghalu","votes":189,"votesFormat":"189","percent":0.03},{"name":"APGA","theme":"blue","candidate":"Gbor John Wilson Terwase","votes":73,"votesFormat":"73","percent":0.01}]},

	{"id":30,"name":"Oyo","leadingParty":{"name":"PDP","theme":"red","candidate":"Atiku Abubakar","votes":366690,"votesFormat":"366,690","percent":43.83},"accredited":905007,"valid":836531,"parties":[{"name":"PDP","theme":"red","candidate":"Atiku Abubakar","votes":366690,"votesFormat":"366,690","percent":43.83},{"name":"APC","theme":"green","candidate":"Muhammadu Buhari","votes":365229,"votesFormat":"365,229","percent":43.66},{"name":"ADC","theme":"yellow","candidate":"Obadiah Mailafia","votes":40830,"votesFormat":"40,830","percent":4.88},{"name":"PCP","theme":"brown","candidate":"Felix Nicolas","votes":5352,"votesFormat":"5,352","percent":0.64},{"name":"AAC","theme":"brown","candidate":"Omoyele Sowore","votes":4014,"votesFormat":"4,014","percent":0.48},{"name":"ANN","theme":"blue","candidate":"Fela Durotoye","votes":1896,"votesFormat":"1,896","percent":0.23},{"name":"YPP","theme":"yellow","candidate":"Kingsley Moghalu","votes":1608,"votesFormat":"1,608","percent":0.19},{"name":"ACPN","theme":"purple","candidate":"Oby Ezekwesili","votes":835,"votesFormat":"835","percent":0.1},{"name":"APGA","theme":"blue","candidate":"Gbor John Wilson Terwase","votes":197,"votesFormat":"197","percent":0.02}]},

	{"id":31,"name":"Plateau","leadingParty":{"name":"PDP","theme":"red","candidate":"Atiku Abubakar","votes":548665,"votesFormat":"548,665","percent":53.02},"accredited":1074042,"valid":1034853,"parties":[{"name":"PDP","theme":"red","candidate":"Atiku Abubakar","votes":548665,"votesFormat":"548,665","percent":53.02},{"name":"APC","theme":"green","candidate":"Muhammadu Buhari","votes":468555,"votesFormat":"468,555","percent":45.28},{"name":"PCP","theme":"brown","candidate":"Felix Nicolas","votes":4276,"votesFormat":"4,276","percent":0.41},{"name":"ANN","theme":"blue","candidate":"Fela Durotoye","votes":796,"votesFormat":"796","percent":0.08},{"name":"ADC","theme":"yellow","candidate":"Obadiah Mailafia","votes":590,"votesFormat":"590","percent":0.06},{"name":"YPP","theme":"yellow","candidate":"Kingsley Moghalu","votes":442,"votesFormat":"442","percent":0.04},{"name":"AAC","theme":"brown","candidate":"Omoyele Sowore","votes":268,"votesFormat":"268","percent":0.03},{"name":"APGA","theme":"blue","candidate":"Gbor John Wilson Terwase","votes":160,"votesFormat":"160","percent":0.02},{"name":"ACPN","theme":"purple","candidate":"Oby Ezekwesili","votes":91,"votesFormat":"91","percent":0.01}]},

	{"id":32,"name":"Rivers","leadingParty":{"name":"PDP","theme":"red","candidate":"Atiku Abubakar","votes":473971,"votesFormat":"473,971","percent":73.81},"accredited":678167,"valid":642165,"parties":[{"name":"PDP","theme":"red","candidate":"Atiku Abubakar","votes":473971,"votesFormat":"473,971","percent":73.81},{"name":"APC","theme":"green","candidate":"Muhammadu Buhari","votes":150710,"votesFormat":"150,710","percent":23.47},{"name":"PCP","theme":"brown","candidate":"Felix Nicolas","votes":2954,"votesFormat":"2,954","percent":0.46},{"name":"APGA","theme":"blue","candidate":"Gbor John Wilson Terwase","votes":614,"votesFormat":"614","percent":0.1},{"name":"ADC","theme":"yellow","candidate":"Obadiah Mailafia","votes":597,"votesFormat":"597","percent":0.09},{"name":"ACPN","theme":"purple","candidate":"Oby Ezekwesili","votes":546,"votesFormat":"546","percent":0.09},{"name":"YPP","theme":"yellow","candidate":"Kingsley Moghalu","votes":415,"votesFormat":"415","percent":0.06},{"name":"AAC","theme":"brown","candidate":"Omoyele Sowore","votes":372,"votesFormat":"372","percent":0.06},{"name":"ANN","theme":"blue","candidate":"Fela Durotoye","votes":365,"votesFormat":"365","percent":0.06}]},

	{"id":33,"name":"Sokoto","leadingParty":{"name":"APC","theme":"green","candidate":"Muhammadu Buhari","votes":490333,"votesFormat":"490,333","percent":56.24},"accredited":950107,"valid":871891,"parties":[{"name":"APC","theme":"green","candidate":"Muhammadu Buhari","votes":490333,"votesFormat":"490,333","percent":56.24},{"name":"PDP","theme":"red","candidate":"Atiku Abubakar","votes":361604,"votesFormat":"361,604","percent":41.47},{"name":"PCP","theme":"brown","candidate":"Felix Nicolas","votes":2630,"votesFormat":"2,630","percent":0.3},{"name":"ADC","theme":"yellow","candidate":"Obadiah Mailafia","votes":331,"votesFormat":"331","percent":0.04},{"name":"APGA","theme":"blue","candidate":"Gbor John Wilson Terwase","votes":313,"votesFormat":"313","percent":0.04},{"name":"AAC","theme":"brown","candidate":"Omoyele Sowore","votes":181,"votesFormat":"181","percent":0.02},{"name":"ACPN","theme":"purple","candidate":"Oby Ezekwesili","votes":146,"votesFormat":"146","percent":0.02},{"name":"ANN","theme":"blue","candidate":"Fela Durotoye","votes":124,"votesFormat":"124","percent":0.01},{"name":"YPP","theme":"yellow","candidate":"Kingsley Moghalu","votes":84,"votesFormat":"84","percent":0.01}]},

	{"id":34,"name":"Taraba","leadingParty":{"name":"PDP","theme":"red","candidate":"Atiku Abubakar","votes":374743,"votesFormat":"374,743","percent":52.57},"accredited":756111,"valid":712877,"parties":[{"name":"PDP","theme":"red","candidate":"Atiku Abubakar","votes":374743,"votesFormat":"374,743","percent":52.57},{"name":"APC","theme":"green","candidate":"Muhammadu Buhari","votes":324906,"votesFormat":"324,906","percent":45.58},{"name":"APGA","theme":"blue","candidate":"Gbor John Wilson Terwase","votes":1071,"votesFormat":"1,071","percent":0.15},{"name":"PCP","theme":"brown","candidate":"Felix Nicolas","votes":321,"votesFormat":"321","percent":0.05},{"name":"ACPN","theme":"purple","candidate":"Oby Ezekwesili","votes":218,"votesFormat":"218","percent":0.03},{"name":"ADC","theme":"yellow","candidate":"Obadiah Mailafia","votes":211,"votesFormat":"211","percent":0.03},{"name":"AAC","theme":"brown","candidate":"Omoyele Sowore","votes":116,"votesFormat":"116","percent":0.02},{"name":"YPP","theme":"yellow","candidate":"Kingsley Moghalu","votes":80,"votesFormat":"80","percent":0.01},{"name":"ANN","theme":"blue","candidate":"Fela Durotoye","votes":35,"votesFormat":"35","percent":0}]},

	{"id":35,"name":"Yobe","leadingParty":{"name":"APC","theme":"green","candidate":"Muhammadu Buhari","votes":497914,"votesFormat":"497,914","percent":89.01},"accredited":601059,"valid":559365,"parties":[{"name":"APC","theme":"green","candidate":"Muhammadu Buhari","votes":497914,"votesFormat":"497,914","percent":89.01},{"name":"PDP","theme":"red","candidate":"Atiku Abubakar","votes":50763,"votesFormat":"50,763","percent":9.08},{"name":"PCP","theme":"brown","candidate":"Felix Nicolas","votes":2107,"votesFormat":"2,107","percent":0.38},{"name":"APGA","theme":"blue","candidate":"Gbor John Wilson Terwase","votes":226,"votesFormat":"226","percent":0.04},{"name":"ADC","theme":"yellow","candidate":"Obadiah Mailafia","votes":162,"votesFormat":"162","percent":0.03},{"name":"AAC","theme":"brown","candidate":"Omoyele Sowore","votes":137,"votesFormat":"137","percent":0.02},{"name":"ACPN","theme":"purple","candidate":"Oby Ezekwesili","votes":94,"votesFormat":"94","percent":0.02},{"name":"ANN","theme":"blue","candidate":"Fela Durotoye","votes":37,"votesFormat":"37","percent":0.01},{"name":"YPP","theme":"yellow","candidate":"Kingsley Moghalu","votes":36,"votesFormat":"36","percent":0.01}]},

	{"id":36,"name":"Zamfara","leadingParty":{"name":"APC","theme":"green","candidate":"Muhammadu Buhari","votes":438682,"votesFormat":"438,682","percent":75.84},"accredited":616168,"valid":578439,"parties":[{"name":"APC","theme":"green","candidate":"Muhammadu Buhari","votes":438682,"votesFormat":"438,682","percent":75.84},{"name":"PDP","theme":"red","candidate":"Atiku Abubakar","votes":125423,"votesFormat":"125,423","percent":21.68},{"name":"PCP","theme":"brown","candidate":"Felix Nicolas","votes":774,"votesFormat":"774","percent":0.13},{"name":"APGA","theme":"blue","candidate":"Gbor John Wilson Terwase","votes":738,"votesFormat":"738","percent":0.13},{"name":"ADC","theme":"yellow","candidate":"Obadiah Mailafia","votes":186,"votesFormat":"186","percent":0.03},{"name":"AAC","theme":"brown","candidate":"Omoyele Sowore","votes":186,"votesFormat":"186","percent":0.03},{"name":"ACPN","theme":"purple","candidate":"Oby Ezekwesili","votes":90,"votesFormat":"90","percent":0.02},{"name":"YPP","theme":"yellow","candidate":"Kingsley Moghalu","votes":44,"votesFormat":"44","percent":0.01},{"name":"ANN","theme":"blue","candidate":"Fela Durotoye","votes":24,"votesFormat":"24","percent":0}]}]